README.md
setup.cfg
setup.py
ffsubs/__init__.py
ffsubs/aligners.py
ffsubs/file_utils.py
ffsubs/generic_subtitles.py
ffsubs/speech_transformers.py
ffsubs/suboffset.py
ffsubs/subsync.py
ffsubs/subtitle_parser.py
ffsubs/subtitle_transformers.py
ffsubs/version.py
ffsubs.egg-info/PKG-INFO
ffsubs.egg-info/SOURCES.txt
ffsubs.egg-info/dependency_links.txt
ffsubs.egg-info/entry_points.txt
ffsubs.egg-info/not-zip-safe
ffsubs.egg-info/requires.txt
ffsubs.egg-info/top_level.txt